{
 "actions": [],
 "allow_rename": 1,
 "creation": "2025-07-27 12:20:18.289095",
 "doctype": "DocType",
 "editable_grid": 1,
 "engine": "InnoDB",
 "field_order": [
  "qr_code",
  "item_code",
  "replacement_qr_code"
 ],
 "fields": [
  {
   "fieldname": "qr_code",
   "fieldtype": "Data",
   "in_list_view": 1,
   "label": "Qr Code"
  },
  {
   "fieldname": "item_code",
   "fieldtype": "Link",
   "in_list_view": 1,
   "label": "Item Code",
   "options": "Item"
  },
  {
   "fieldname": "replacement_qr_code",
   "fieldtype": "Data",
   "in_list_view": 1,
   "label": "Replacement Qr Code"
  }
 ],
 "index_web_pages_for_search": 1,
 "istable": 1,
 "links": [],
 "modified": "2025-07-27 12:21:23.187878",
 "modified_by": "Administrator",
 "module": "Track",
 "name": "Repack Code",
 "owner": "Administrator",
 "permissions": [],
 "sort_field": "modified",
 "sort_order": "DESC",
 "states": []
}